c/crc.c
imagebackup/__init__.py
imagebackup/blockio.py
imagebackup/crc.cpython-38-x86_64-linux-gnu.so
imagebackup/fuse.py
imagebackup/imagebackup.py
imagebackup/main.py
imagebackup/ntfsclone.py
imagebackup/partclone.py
imagebackup/partimage.py
imagebackup/utilities.py
imagebackup-0.2.1.dist-info/LICENSE
imagebackup-0.2.1.dist-info/METADATA
imagebackup-0.2.1.dist-info/WHEEL
imagebackup-0.2.1.dist-info/entry_points.txt
imagebackup-0.2.1.dist-info/top_level.txt
imagebackup-0.2.1.dist-info/RECORD
